<BackupInst xmlns="http://www.microsoft.com/GroupPolicy/GPOOperations/Manifest"><GPOGuid><![CDATA[{62313F52-5CE0-4AE5-A963-16076A6680DA}]]></GPOGuid><GPODomain><![CDATA[labs.local]]></GPODomain><GPODomainGuid><![CDATA[{05c56471-6cb0-4490-9ab1-236f871ecd91}]]></GPODomainGuid><GPODomainController><![CDATA[dc01.labs.local]]></GPODomainController><BackupTime><![CDATA[2020-09-10T02:45:43]]></BackupTime><ID><![CDATA[{36590439-CB1C-44CD-9171-AF75DBF163CC}]]></ID><Comment><![CDATA[Windows Event Forwarding]]></Comment><GPODisplayName><![CDATA[Windows Event Forwarding]]></GPODisplayName></BackupInst>
